.gitignore
.gitmodules
.travis.yml
AUTHORS
CMakeLists.txt
CPPLINT.cfg
Doxyfile
LICENSE
MANIFEST.in
README.md
compile.sh
setup.py
benchmarks/CMakeLists.txt
benchmarks/api/CMakeLists.txt
benchmarks/api/generate_numbers.cpp
benchmarks/api/generate_write_binary.cpp
benchmarks/api/groupby.cpp
benchmarks/api/groupby2.cpp
benchmarks/api/groupby_unequal_keys.cpp
benchmarks/api/merge.cpp
benchmarks/api/read_write_lines.cpp
benchmarks/api/sort.cpp
benchmarks/api/string_test.cpp
benchmarks/core/duplicates_speedup_benchmark.cpp
benchmarks/core/golomb_code_benchmark.cpp
benchmarks/core/golomb_code_benchmark.py
benchmarks/data/CMakeLists.txt
benchmarks/data/data_benchmark.cpp
benchmarks/data/data_generators.hpp
benchmarks/data/run_data_benchmark.sh
benchmarks/hashtable/bench_bucket_hashtable.py
benchmarks/hashtable/bench_hashtable.cpp
benchmarks/hashtable/bench_hashtable.py
benchmarks/hashtable/bench_probing_hashtable.py
benchmarks/hashtable/generate_data.cpp
benchmarks/hashtable/graph_gen.py
benchmarks/hashtable/reduce.cpp
benchmarks/mem/CMakeLists.txt
benchmarks/mem/pool_benchmark.cpp
benchmarks/net/CMakeLists.txt
benchmarks/net/net_benchmark.cpp
benchmarks/serialization/bench_serialization.cpp
benchmarks/serialization/cpp-serializers.cpp
benchmarks/serialization/data.hpp
doc/api.dox
doc/common.dox
doc/data.dox
doc/main.dox
doc/mem.dox
doc/net.dox
doc/start.dox
doc/style_guide.dox
doc/images/byteblock-file.pdf
doc/images/byteblock-file.svg
doc/images/cluster-execution.pdf
doc/images/cluster-execution.svg
doc/images/dc7-dataflow.svg
doc/images/exec-profile.html
doc/images/k-means.png
doc/images/dia_ops/AllGather.svg
doc/images/dia_ops/AllReduce.svg
doc/images/dia_ops/ConcatToDIA.svg
doc/images/dia_ops/EqualToDIA.svg
doc/images/dia_ops/ExPrefixSum.svg
doc/images/dia_ops/Filter.svg
doc/images/dia_ops/FlatMap.svg
doc/images/dia_ops/Generate.svg
doc/images/dia_ops/GroupByKey.svg
doc/images/dia_ops/GroupToIndex.svg
doc/images/dia_ops/Map.svg
doc/images/dia_ops/Merge.svg
thrill.egg-info/PKG-INFO
thrill.egg-info/SOURCES.txt
thrill.egg-info/dependency_links.txt
thrill.egg-info/not-zip-safe
thrill.egg-info/top_level.txt
