Metadata-Version: 2.1
Name: thrill
Version: 0.0.1
Summary: Thrill - Distributed Big Data Batch Processing Framework in C++
Home-page: https://project-thrill.org
Author: Timo Bingmann
Author-email: tbdev@panthema.net
License: UNKNOWN
Platform: UNKNOWN
Classifier: Development Status :: 3 - Alpha
Classifier: Programming Language :: C++
Classifier: Topic :: System :: Distributed Computing
Classifier: Topic :: Software Development :: Libraries :: Application Frameworks
